api/generated/google/api/annotations_pb2.py
api/generated/google/api/annotations_pb2_grpc.py
api/generated/google/api/field_behavior_pb2.py
api/generated/google/api/field_behavior_pb2_grpc.py
api/generated/google/api/http_pb2.py
api/generated/google/api/http_pb2_grpc.py
api/generated/google/api/httpbody_pb2.py
api/generated/google/api/httpbody_pb2_grpc.py
api/generated/openapiv3/OpenAPIv3_pb2.py
api/generated/openapiv3/OpenAPIv3_pb2_grpc.py
api/generated/openapiv3/annotations_pb2.py
api/generated/openapiv3/annotations_pb2_grpc.py
api/generated/server/v1/api_pb2.py
api/generated/server/v1/api_pb2_grpc.py
api/generated/server/v1/auth_pb2.py
api/generated/server/v1/auth_pb2_grpc.py
api/generated/server/v1/observability_pb2.py
api/generated/server/v1/observability_pb2_grpc.py
api/generated/server/v1/search_pb2.py
api/generated/server/v1/search_pb2_grpc.py
tigrisdb/__init__.py
tigrisdb/auth.py
tigrisdb/client.py
tigrisdb/collection.py
tigrisdb/database.py
tigrisdb/errors.py
tigrisdb/search.py
tigrisdb/search_index.py
tigrisdb/types/__init__.py
tigrisdb/types/filters/__init__.py
tigrisdb/types/filters/logical.py
tigrisdb/types/filters/selector.py
tigrisdb/types/search.py
tigrisdb/types/sort.py
tigrisdb/types/vector.py
tigrisdb/utils.py
tigrisdb/vector_store.py
tigrisdb-1.0.0b6.dist-info/LICENSE
tigrisdb-1.0.0b6.dist-info/METADATA
tigrisdb-1.0.0b6.dist-info/WHEEL
tigrisdb-1.0.0b6.dist-info/entry_points.txt
tigrisdb-1.0.0b6.dist-info/RECORD
