Metadata-Version: 2.1
Name: tigrisdb
Version: 1.0.0b6
Summary: Python SDK for Tigris <http://www.tigrisdata.com>
Home-page: https://www.github.com/tigrisdata/tigris-client-python
License: Apache-2.0
Keywords: database,nosql,vector,search
Author: Tigris team
Author-email: support@tigrisdata.com
Requires-Python: >=3.8,<4.0
Classifier: Development Status :: 4 - Beta
Classifier: Intended Audience :: Developers
Classifier: License :: OSI Approved :: Apache Software License
Classifier: Programming Language :: Python :: 3
Classifier: Programming Language :: Python :: 3.8
Classifier: Programming Language :: Python :: 3.9
Classifier: Programming Language :: Python :: 3.10
Classifier: Programming Language :: Python :: 3.11
Classifier: Topic :: Database
Requires-Dist: grpcio-tools (>=1.46.0)
Requires-Dist: protobuf (>=3.19.6)
Project-URL: Documentation, https://www.tigrisdata.com/docs/
Project-URL: Repository, https://www.github.com/tigrisdata/tigris-client-python
